{
  "updated": "2026-07-22T21:59:48.895Z",
  "live": [
    {
      "id": 6,
      "n": "Jotape Arcade",
      "videoId": "RccnfTBKtXM",
      "videoTitle": "Warzone evento de Halloween 2021",
      "videoUrl": "https://www.youtube.com/watch?v=RccnfTBKtXM",
      "thumbnail": "https://i.ytimg.com/vi/RccnfTBKtXM/hqdefault.jpg"
    },
    {
      "id": 9,
      "n": "Rodrigo Retro Games",
      "videoId": "x5NhNyhmLFo",
      "videoTitle": "LIVE DE VENDAS! (Rodrigo Games)",
      "videoUrl": "https://www.youtube.com/watch?v=x5NhNyhmLFo",
      "thumbnail": "https://i.ytimg.com/vi/x5NhNyhmLFo/hqdefault.jpg"
    }
  ]
}
